afif/__init__.py
afif/helloworld.py
afif/node.py
afif-0.2.1.dist-info/METADATA
afif-0.2.1.dist-info/WHEEL
afif-0.2.1.dist-info/top_level.txt
afif-0.2.1.dist-info/RECORD
