Metadata-Version: 2.1
Name: afif
Version: 0.2.1
Summary: this package is create to remembering me about create, install, use in local, and publishing in pipy
Home-page: UNKNOWN
Author: Muhammad Afif Nur Azizi
Author-email: afifnurazizi@gmail.com
License: MIT
Platform: UNKNOWN
